[{"id":99,"pid":6,"name":"Kabupaten Banyuasin","ibukota":"Pangkalan Balai","bsni":"PKB","hash":"9ed5ff214b1730bda255fe819f3b0b58"},{"id":100,"pid":6,"name":"Kabupaten Empat Lawang","ibukota":"Tebing Tinggi","bsni":"TBG","hash":"a9751f0c83bc533b4a4cf474c54802c8"},{"id":101,"pid":6,"name":"Kabupaten Lahat","ibukota":"Lahat","bsni":"LHT","hash":"717a49187195dae3d0ad32f60eda198c"},{"id":102,"pid":6,"name":"Kabupaten Muara Enim","ibukota":"Muara Enim","bsni":"MRE","hash":"3f8edb37173c20d59aaadb96daf6a538"},{"id":103,"pid":6,"name":"Kabupaten Musi Banyuasin","ibukota":"Sekayu","bsni":"SKY","hash":"6205bf33d6ddf01ffed122474711c002"},{"id":104,"pid":6,"name":"Kabupaten Musi Rawas","ibukota":"Muarabeliti","bsni":"MBL","hash":"765de6ef17e97109152331d280653acb"},{"id":105,"pid":6,"name":"Kabupaten Musi Rawas Utara","ibukota":"Rupit","bsni":"RPT","hash":"26b2633476eb21b47bf532bfcfa7b199"},{"id":106,"pid":6,"name":"Kabupaten Ogan Ilir","ibukota":"Indralaya","bsni":"IDL","hash":"75721fef75b7728e66d94b0857b977e8"},{"id":107,"pid":6,"name":"Kabupaten Ogan Komering Ilir","ibukota":"Kayu Agung","bsni":"KAG","hash":"90170de55691582cec8a685c443dc1f2"},{"id":108,"pid":6,"name":"Kabupaten Ogan Komering Ulu","ibukota":"Baturaja","bsni":"BTA","hash":"8915c4871b67554484e33f82e156b1b8"},{"id":109,"pid":6,"name":"Kabupaten Ogan Komering Ulu Selatan (Oku Selatan)","ibukota":"Muaradua","bsni":"MRD","hash":"6996b4866255e4cc6633cd8e91dc98ea"},{"id":110,"pid":6,"name":"Kabupaten Ogan Komering Ulu Timur (Oku Timur)","ibukota":"Martapura","bsni":"MPR","hash":"fe3be24fb3a61245301d933b88ef5aa1"},{"id":111,"pid":6,"name":"Kabupaten Penukal Abab Lematang Ilir","ibukota":"Talang Ubi","bsni":"TLB","hash":"e5e22806a760948dab2eaa34b4c95767"},{"id":112,"pid":6,"name":"Kota Lubuk Linggau","ibukota":"Lubuk Linggau","bsni":"LLG","hash":"1bda41e9d688a170a64ddfaa9385d07f"},{"id":113,"pid":6,"name":"Kota Pagar Alam","ibukota":"Pagar Alam","bsni":"PGA","hash":"415dffc65eec3d73ec59c754ef4a529b"},{"id":114,"pid":6,"name":"Kota Palembang","ibukota":"Pelembang","bsni":"PLG","hash":"7b27a619f12e92844c6e89ff64dc958c"},{"id":115,"pid":6,"name":"Kota Prabumulih","ibukota":"Prabumulih","bsni":"PBM","hash":"d3a17af50bfcbe258a393fb581c032cf"}]
